README.md
setup.py
nbtest_legoSrvTest/__init__.py
nbtest_legoSrvTest/_nbtest_legoSrvTest.py
nbtest_legoSrvTest.egg-info/PKG-INFO
nbtest_legoSrvTest.egg-info/SOURCES.txt
nbtest_legoSrvTest.egg-info/dependency_links.txt
nbtest_legoSrvTest.egg-info/requires.txt
nbtest_legoSrvTest.egg-info/top_level.txt
nbtest_legoSrvTest.egg-info/zip-safe