Metadata-Version: 1.1
Name: nbtest-legoSrvTest
Version: 0.1.0
Summary: nbtest_legoSrvTest
Home-page: https://github.com/jayvee-yjw/nbtest_legoSrvTest
Author: jayvee-yjw
Author-email: gmkingyao001@gmail.com
License: UNKNOWN
Download-URL: https://github.com/jayvee-yjw/nbtest_legoSrvTest/archive/master.zip
Keywords: nbtest_legoSrvTest
Platform: UNKNOWN
